skinny_telegram_bot_wrapper/__init__.py
skinny_telegram_bot_wrapper/bot.py
skinny_telegram_bot_wrapper/main.py
skinny_telegram_bot_wrapper/request_handler.py
skinny_telegram_bot_wrapper/telegram_update_handlers.py
skinny_telegram_bot_wrapper/update_handler.py
skinny_telegram_bot_wrapper/utilities.py
skinny_telegram_bot_wrapper-0.2.4.dist-info/LICENSE.txt
skinny_telegram_bot_wrapper-0.2.4.dist-info/METADATA
skinny_telegram_bot_wrapper-0.2.4.dist-info/WHEEL
skinny_telegram_bot_wrapper-0.2.4.dist-info/top_level.txt
skinny_telegram_bot_wrapper-0.2.4.dist-info/RECORD
